langdive/__init__.py
langdive/corpus_processing.py
langdive/langdive.py
langdive/polyglot_tokenizer.py
langdive/data/bible.10000.stats.tsv
langdive/data/mbert.10000.stats.tsv
langdive/data/teddi.10000.stats.tsv
langdive/data/tydiqa.10000.stats.tsv
langdive/data/ud.10000.stats.tsv
langdive/data/xcopa.10000.stats.tsv
langdive/data/xglue.10000.stats.tsv
langdive/data/xnli.10000.stats.tsv
langdive/data/xquad.10000.stats.tsv
langdive/data/xtreme.10000.stats.tsv
langdive-1.0.dist-info/LICENCE
langdive-1.0.dist-info/METADATA
langdive-1.0.dist-info/WHEEL
langdive-1.0.dist-info/top_level.txt
langdive-1.0.dist-info/RECORD
