Metadata-Version: 2.1
Name: langdive
Version: 1.0
Summary: LangDive is a library for measuring the level of linguistic diversity in multilingual NLP datasets
Author-email: Natural Language Processing group at the Innovation Center of the School of Electrical Engineering in Belgrade <vuk.batanovic@ic.etf.bg.ac.rs>
Project-URL: Homepage, https://github.com/ICEF-NLP/jmm_diversity/tree/langdive-lib
Classifier: Programming Language :: Python :: 3
Classifier: Operating System :: OS Independent
Classifier: License :: OSI Approved :: GNU General Public License v3 or later (GPLv3+)
Classifier: Development Status :: 5 - Production/Stable
Requires-Python: >=3.10
License-File: LICENCE
Requires-Dist: setuptools >=72.1.0
Requires-Dist: scipy >=1.14.0
Requires-Dist: lang2vec >=1.1.2
Requires-Dist: PyICU >=2.13
Requires-Dist: pandas >=2.2.2
Requires-Dist: seaborn >=0.13.2
Requires-Dist: segments >=2.2.1
Requires-Dist: six >=1.16.0
